CHANGELOG.md
LICENSE
MANIFEST.in
README.md
README.rst
example.py
setup.py
test_gevent_inotifyx.py
gevent_inotifyx/__init__.py
gevent_inotifyx.egg-info/PKG-INFO
gevent_inotifyx.egg-info/SOURCES.txt
gevent_inotifyx.egg-info/dependency_links.txt
gevent_inotifyx.egg-info/requires.txt
gevent_inotifyx.egg-info/top_level.txt
gevent_inotifyx/vendor/__init__.py
gevent_inotifyx/vendor/inotifyx/__init__.py
gevent_inotifyx/vendor/inotifyx/binding.c
gevent_inotifyx/vendor/inotifyx/distinfo.py