Metadata-Version: 1.1
Name: gevent_inotifyx
Version: 0.2
Summary: gevent compatibility for inotifyx
Home-page: https://github.com/trendels/gevent_inotifyx
Author: Stanis Trendelenburg
Author-email: stanis.trendelenburg@gmail.com
License: MIT
Platform: UNKNOWN
Classifier: License :: OSI Approved :: MIT License
Classifier: Programming Language :: Python
Classifier: Programming Language :: Python :: 2
Classifier: Programming Language :: Python :: 3
